ddpm_proteins/__init__.py
ddpm_proteins/ddpm_proteins.py
ddpm_proteins/utils.py
ddpm_proteins-0.0.11.dist-info/LICENSE
ddpm_proteins-0.0.11.dist-info/METADATA
ddpm_proteins-0.0.11.dist-info/WHEEL
ddpm_proteins-0.0.11.dist-info/top_level.txt
ddpm_proteins-0.0.11.dist-info/RECORD
